CODE_OF_CONDUCT.md
CONTRIBUTING.md
LICENSE
MANIFEST.in
Makefile
README.md
demucs.png
mypy.ini
outputs.tar.gz
requirements.txt
requirements_minimal.txt
setup.cfg
setup.py
test.mp3
conf/config.yaml
conf/dset/aetl.yaml
conf/dset/auto_extra_test.yaml
conf/dset/auto_mus.yaml
conf/dset/extra44.yaml
conf/dset/extra_mmi_goodclean.yaml
conf/dset/extra_test.yaml
conf/dset/musdb44.yaml
conf/svd/base.yaml
conf/svd/base2.yaml
conf/svd/default.yaml
conf/variant/default.yaml
conf/variant/example.yaml
conf/variant/finetune.yaml
demucs/__init__.py
demucs/__main__.py
demucs/apply.py
demucs/audio.py
demucs/augment.py
demucs/demucs.py
demucs/distrib.py
demucs/ema.py
demucs/evaluate.py
demucs/hdemucs.py
demucs/htdemucs.py
demucs/pretrained.py
demucs/py.typed
demucs/repitch.py
demucs/repo.py
demucs/separate.py
demucs/solver.py
demucs/spec.py
demucs/states.py
demucs/svd.py
demucs/train.py
demucs/transformer.py
demucs/utils.py
demucs/wav.py
demucs/wdemucs.py
demucs.egg-info/PKG-INFO
demucs.egg-info/SOURCES.txt
demucs.egg-info/dependency_links.txt
demucs.egg-info/entry_points.txt
demucs.egg-info/requires.txt
demucs.egg-info/top_level.txt
demucs/remote/files.txt
demucs/remote/hdemucs_mmi.yaml
demucs/remote/htdemucs.yaml
demucs/remote/htdemucs_6s.yaml
demucs/remote/htdemucs_ft.yaml
demucs/remote/mdx.yaml
demucs/remote/mdx_extra.yaml
demucs/remote/mdx_extra_q.yaml
demucs/remote/mdx_q.yaml
demucs/remote/repro_mdx_a.yaml
demucs/remote/repro_mdx_a_hybrid_only.yaml
demucs/remote/repro_mdx_a_time_only.yaml