Metadata-Version: 2.1
Name: demucs
Version: 4.0.0
Summary: Music source separation in the waveform domain.
Home-page: https://github.com/facebookresearch/demucs
Author: Alexandre Défossez
Author-email: defossez@fb.com
License: MIT License
Platform: UNKNOWN
Classifier: License :: OSI Approved :: MIT License
Classifier: Topic :: Multimedia :: Sound/Audio
Classifier: Topic :: Scientific/Engineering :: Artificial Intelligence
Requires-Python: >=3.7.0
Provides-Extra: dev
